purehtml/__init__.py
purehtml/constants.py
purehtml/html2md.py
purehtml/purehtml.py
purehtml-0.7.5.dist-info/LICENSE
purehtml-0.7.5.dist-info/METADATA
purehtml-0.7.5.dist-info/WHEEL
purehtml-0.7.5.dist-info/top_level.txt
purehtml-0.7.5.dist-info/RECORD
