Metadata-Version: 2.1
Name: purehtml
Version: 0.7.5
Summary: Purify HTML by filtering tags and classes
Author: Hansimov
Project-URL: Homepage, https://github.com/Hansimov/pure-html
Project-URL: Issues, https://github.com/Hansimov/pure-html/issues
Classifier: Programming Language :: Python :: 3
Classifier: License :: OSI Approved :: MIT License
Classifier: Operating System :: OS Independent
Requires-Python: >=3.6
License-File: LICENSE
Requires-Dist: tclogger
Requires-Dist: beautifulsoup4
